notified/__init__.py
notified/client.py
notified/config.py
notified/handlers.py
notified/server.py
notified/utils.py
notified-0.1.0.dist-info/LICENSE
notified-0.1.0.dist-info/METADATA
notified-0.1.0.dist-info/WHEEL
notified-0.1.0.dist-info/RECORD
