Metadata-Version: 2.1
Name: notified
Version: 0.1.0
Summary: Simple pub/sub implementation using PostgreSQL events.
Home-page: https://github.com/aleosd/motified
License: Apache-2.0
Author: Alex Osadchuk
Author-email: alxosd@proton.me
Requires-Python: >=3.10,<4.0
Classifier: Development Status :: 4 - Beta
Classifier: License :: OSI Approved :: Apache Software License
Classifier: Programming Language :: Python :: 3
Classifier: Programming Language :: Python :: 3.10
Classifier: Programming Language :: Python :: 3.11
Classifier: Programming Language :: Python :: 3.12
Classifier: Programming Language :: Python :: 3.13
Classifier: Topic :: Database
Requires-Dist: nanos (>=0.1.5,<0.2.0)
Requires-Dist: psycopg2-binary (>=2.9,<3.0)
Project-URL: Documentation, https://github.com/aleosd/notified
Project-URL: Repository, https://github.com/aleosd/notified
